[
    {
        "email": "shaho@gmail.com",
        "movie": "tt4154664",
        "like": false
    },
    {
        "email": "shaho@gmail.com",
        "movie": "tt0110912",
        "like": true
    },
    {
        "email": "Rayan.d15@outlook.com",
        "movie": "tt0295297",
        "like": true
    },
    {
        "email": "Rayan.d15@outlook.com",
        "movie": "tt1430132",
        "like": true
    },
    {
        "email": "Rayan.d15@outlook.com",
        "movie": "tt0120737",
        "like": true
    },
    {
        "email": "Rayan.d15@outlook.com",
        "movie": "tt0974015",
        "like": false
    }
]